{
  "custom": {},
  "params": {
    "D1": "N/A",
    "D2": "N/A",
    "End1": "N/A",
    "End2": "N/A",
    "Start1": "N/A",
    "Start2": "N/A",
    "calres": "",
    "calresmy": "",
    "item": "",
    "swap": 0,
    "task1": {
      "clickCount": 0,
      "firstId": null,
      "secondId": null
    }
  },
  "propConfig": {
    "params.D1": {
      "binding": {
        "config": {
          "parameters": {
            "event1": "{view.params.task1.firstId}"
          },
          "queryPath": "Swap duration 1"
        },
        "transforms": [
          {
            "code": "\tfrom java.text import SimpleDateFormat\n\t\n\tpyData \u003d system.dataset.toPyDataSet(value)\n\t\n\tif pyData and len(pyData) \u003e 0:\n\t    raw_date \u003d pyData[0][0]  # First row, first column\n#\t    if raw_date:\n#\t        sdf \u003d SimpleDateFormat(\"MM/dd/yy HH:mm\")\n#\t        formatted_date \u003d sdf.format(raw_date)\n\t    return raw_date\n\telse:\n\t    return \"N/A\"",
            "type": "script"
          }
        ],
        "type": "query"
      },
      "paramDirection": "inout",
      "persistent": true
    },
    "params.D2": {
      "binding": {
        "config": {
          "parameters": {
            "event2": "{view.params.task1.secondId}"
          },
          "queryPath": "swap duration 2"
        },
        "transforms": [
          {
            "code": "\tfrom java.text import SimpleDateFormat\n\t\n\tpyData \u003d system.dataset.toPyDataSet(value)\n\t\n\tif pyData and len(pyData) \u003e 0:\n\t    raw_date \u003d pyData[0][0]  # First row, first column\n#\t    if raw_date:\n#\t        sdf \u003d SimpleDateFormat(\"MM/dd/yy HH:mm\")\n#\t        formatted_date \u003d sdf.format(raw_date)\n\t    return raw_date\n\telse:\n\t    return \"N/A\"",
            "type": "script"
          }
        ],
        "type": "query"
      },
      "paramDirection": "inout",
      "persistent": true
    },
    "params.End1": {
      "binding": {
        "config": {
          "parameters": {
            "event1": "{view.params.task1.firstId}"
          },
          "queryPath": "FetchEnd1"
        },
        "transforms": [
          {
            "code": "\tfrom java.text import SimpleDateFormat\n\t\n\tpyData \u003d system.dataset.toPyDataSet(value)\n\t\n\tif pyData and len(pyData) \u003e 0:\n\t    raw_date \u003d pyData[0][0]  # First row, first column\n\t    if raw_date:\n\t        sdf \u003d SimpleDateFormat(\"MM/dd/yy HH:mm\")\n\t        formatted_date \u003d sdf.format(raw_date)\n\t        return formatted_date\n\t    else:\n\t        return \"N/A\"\n\telse:\n\t    return \"N/A\"",
            "type": "script"
          }
        ],
        "type": "query"
      },
      "paramDirection": "inout",
      "persistent": true
    },
    "params.End2": {
      "binding": {
        "config": {
          "parameters": {
            "event2": "{view.params.task1.secondId}"
          },
          "queryPath": "FetchEnd2"
        },
        "transforms": [
          {
            "code": "\tfrom java.text import SimpleDateFormat\n\t\n\tpyData \u003d system.dataset.toPyDataSet(value)\n\t\n\tif pyData and len(pyData) \u003e 0:\n\t    raw_date \u003d pyData[0][0]  # First row, first column\n\t    if raw_date:\n\t        sdf \u003d SimpleDateFormat(\"MM/dd/yy HH:mm\")\n\t        formatted_date \u003d sdf.format(raw_date)\n\t        return formatted_date\n\t    else:\n\t        return \"N/A\"\n\telse:\n\t    return \"N/A\"",
            "type": "script"
          }
        ],
        "type": "query"
      },
      "paramDirection": "inout",
      "persistent": true
    },
    "params.Start1": {
      "binding": {
        "config": {
          "parameters": {
            "event1": "{view.params.task1.firstId}"
          },
          "queryPath": "FetchStart1"
        },
        "transforms": [
          {
            "code": "\tfrom java.text import SimpleDateFormat\n\t\n\tpyData \u003d system.dataset.toPyDataSet(value)\n\t\n\tif pyData and len(pyData) \u003e 0:\n\t    raw_date \u003d pyData[0][0]  # First row, first column\n\t    if raw_date:\n\t        sdf \u003d SimpleDateFormat(\"MM/dd/yy HH:mm\")\n\t        formatted_date \u003d sdf.format(raw_date)\n\t        return formatted_date\n\t    else:\n\t        return \"N/A\"\n\telse:\n\t    return \"N/A\"",
            "type": "script"
          }
        ],
        "type": "query"
      },
      "paramDirection": "inout",
      "persistent": true
    },
    "params.Start2": {
      "binding": {
        "config": {
          "parameters": {
            "event2": "{view.params.task1.secondId}"
          },
          "queryPath": "FetchStart2"
        },
        "transforms": [
          {
            "code": "\tfrom java.text import SimpleDateFormat\n\t\n\tpyData \u003d system.dataset.toPyDataSet(value)\n\t\n\tif pyData and len(pyData) \u003e 0:\n\t    raw_date \u003d pyData[0][0]  # First row, first column\n\t    if raw_date:\n\t        sdf \u003d SimpleDateFormat(\"MM/dd/yy HH:mm\")\n\t        formatted_date \u003d sdf.format(raw_date)\n\t        return formatted_date\n\t    else:\n\t        return \"N/A\"\n\telse:\n\t    return \"N/A\"",
            "type": "script"
          }
        ],
        "type": "query"
      },
      "paramDirection": "inout",
      "persistent": true
    },
    "params.calres": {
      "paramDirection": "inout",
      "persistent": true
    },
    "params.calresmy": {
      "binding": {
        "config": {
          "path": "view.params.calres"
        },
        "transforms": [
          {
            "code": "\tfrom java.text import SimpleDateFormat\n\t\n\tpyData \u003d system.dataset.toPyDataSet(value)\n\t\n\tif pyData and len(pyData) \u003e 0:\n\t    raw_date \u003d pyData[0][0]  # First row, first column\n\t    if raw_date:\n\t        sdf \u003d SimpleDateFormat(\"MM/dd/yy HH:mm\")\n\t        formatted_date \u003d sdf.format(raw_date)\n\t        return formatted_date\n\t    else:\n\t        return \"N/A\"\n\telse:\n\t    return \"N/A\"",
            "type": "script"
          }
        ],
        "type": "property"
      },
      "paramDirection": "inout",
      "persistent": true
    },
    "params.item": {
      "paramDirection": "inout",
      "persistent": true
    },
    "params.swap": {
      "paramDirection": "inout",
      "persistent": true
    },
    "params.task1": {
      "paramDirection": "inout",
      "persistent": true
    }
  },
  "props": {
    "defaultSize": {
      "height": 600,
      "width": 1164
    }
  },
  "root": {
    "children": [
      {
        "events": {
          "component": {
            "onEditCellCommit": {
              "config": {
                "script": "\t# Only handle edits to the \"Remark\" column\n\tif event.column \u003d\u003d \"Remark\":\n\t    newRemark \u003d event.value\n\t    rowIndex \u003d event.row\n#\t    rid \u003d self.props.data[rowIndex][\"RID\"]\n\t\t\n\t\t# Convert dataset to PyDataSet\n\t    data \u003d system.dataset.toPyDataSet(self.props.data)\n\t\n\t    # Now you can access it like a list of dictionaries\n\t    rid \u003d data[rowIndex][\"RID\"]\n\t\n\t    # Call the named query to update the database\n\t    system.db.runNamedQuery(\n\t        \"Remarkadd\",  # Adjust path if it\u0027s in a folder\n\t        {\n\t            \"newRemark\": newRemark,\n\t            \"rid\": rid\n\t        }\n\t    )\n\t\t\n#\t    Optional: Refresh the table data if it\u0027s bound to a query\n\t    self.refreshBinding(\"props.data\")"
              },
              "scope": "G",
              "type": "script"
            }
          }
        },
        "meta": {
          "name": "ReqTable"
        },
        "position": {
          "height": 0.425,
          "width": 0.9837,
          "x": 0.0066,
          "y": 0.5597
        },
        "propConfig": {
          "props.columns[9].visible": {
            "binding": {
              "config": {
                "expression": "if({session.props.auth.user.roles[0]} \u003d \u0027Administrator\u0027,true,false)"
              },
              "type": "expr"
            }
          },
          "props.data": {
            "binding": {
              "config": {
                "polling": {
                  "enabled": true,
                  "rate": "3"
                },
                "queryPath": "ReqTableQuery"
              },
              "type": "query"
            }
          }
        },
        "props": {
          "columns": [
            {
              "align": "center",
              "boolean": "checkbox",
              "dateFormat": "MM/DD/YYYY",
              "editable": false,
              "field": "RID",
              "filter": {
                "boolean": {
                  "condition": ""
                },
                "date": {
                  "condition": "",
                  "value": ""
                },
                "enabled": false,
                "number": {
                  "condition": "",
                  "value": ""
                },
                "string": {
                  "condition": "",
                  "value": ""
                },
                "visible": "on-hover"
              },
              "footer": {
                "align": "center",
                "justify": "left",
                "style": {
                  "classes": ""
                },
                "title": ""
              },
              "header": {
                "align": "center",
                "justify": "center",
                "style": {
                  "classes": ""
                },
                "title": "ID"
              },
              "justify": "center",
              "nullFormat": {
                "includeNullStrings": false,
                "nullFormatValue": "",
                "strict": false
              },
              "number": "value",
              "numberFormat": "0,0.##",
              "progressBar": {
                "bar": {
                  "color": "",
                  "style": {
                    "classes": ""
                  }
                },
                "max": 100,
                "min": 0,
                "track": {
                  "color": "",
                  "style": {
                    "classes": ""
                  }
                },
                "value": {
                  "enabled": true,
                  "format": "0,0.##",
                  "justify": "center",
                  "style": {
                    "classes": ""
                  }
                }
              },
              "render": "auto",
              "resizable": true,
              "sort": "descending",
              "sortable": true,
              "strictWidth": false,
              "style": {
                "classes": ""
              },
              "toggleSwitch": {
                "color": {
                  "selected": "",
                  "unselected": ""
                }
              },
              "viewParams": {},
              "viewPath": "",
              "visible": true,
              "width": 40
            },
            {
              "align": "center",
              "boolean": "checkbox",
              "dateFormat": "MM/DD/YY hh:mm",
              "editable": false,
              "field": "RequestTime",
              "filter": {
                "boolean": {
                  "condition": ""
                },
                "date": {
                  "condition": "",
                  "value": ""
                },
                "enabled": false,
                "number": {
                  "condition": "",
                  "value": ""
                },
                "string": {
                  "condition": "",
                  "value": ""
                },
                "visible": "on-hover"
              },
              "footer": {
                "align": "center",
                "justify": "left",
                "style": {
                  "classes": ""
                },
                "title": ""
              },
              "header": {
                "align": "center",
                "justify": "center",
                "style": {
                  "classes": ""
                },
                "title": "Request Time"
              },
              "justify": "center",
              "nullFormat": {
                "includeNullStrings": false,
                "nullFormatValue": "",
                "strict": false
              },
              "number": "value",
              "numberFormat": "0,0.##",
              "progressBar": {
                "bar": {
                  "color": "",
                  "style": {
                    "classes": ""
                  }
                },
                "max": 100,
                "min": 0,
                "track": {
                  "color": "",
                  "style": {
                    "classes": ""
                  }
                },
                "value": {
                  "enabled": true,
                  "format": "0,0.##",
                  "justify": "center",
                  "style": {
                    "classes": ""
                  }
                }
              },
              "render": "auto",
              "resizable": true,
              "sort": "descending",
              "sortable": true,
              "strictWidth": false,
              "style": {
                "classes": ""
              },
              "toggleSwitch": {
                "color": {
                  "selected": "",
                  "unselected": ""
                }
              },
              "viewParams": {},
              "viewPath": "",
              "visible": true,
              "width": ""
            },
            {
              "align": "center",
              "boolean": "checkbox",
              "dateFormat": "MM/DD/YYYY",
              "editable": false,
              "field": "Department",
              "filter": {
                "boolean": {
                  "condition": ""
                },
                "date": {
                  "condition": "",
                  "value": ""
                },
                "enabled": false,
                "number": {
                  "condition": "",
                  "value": ""
                },
                "string": {
                  "condition": "",
                  "value": ""
                },
                "visible": "on-hover"
              },
              "footer": {
                "align": "center",
                "justify": "left",
                "style": {
                  "classes": ""
                },
                "title": ""
              },
              "header": {
                "align": "center",
                "justify": "center",
                "style": {
                  "classes": ""
                },
                "title": "Resource"
              },
              "justify": "center",
              "nullFormat": {
                "includeNullStrings": false,
                "nullFormatValue": "",
                "strict": false
              },
              "number": "value",
              "numberFormat": "0,0.##",
              "progressBar": {
                "bar": {
                  "color": "",
                  "style": {
                    "classes": ""
                  }
                },
                "max": 100,
                "min": 0,
                "track": {
                  "color": "",
                  "style": {
                    "classes": ""
                  }
                },
                "value": {
                  "enabled": true,
                  "format": "0,0.##",
                  "justify": "center",
                  "style": {
                    "classes": ""
                  }
                }
              },
              "render": "auto",
              "resizable": true,
              "sort": "none",
              "sortable": false,
              "strictWidth": false,
              "style": {
                "classes": ""
              },
              "toggleSwitch": {
                "color": {
                  "selected": "",
                  "unselected": ""
                }
              },
              "viewParams": {},
              "viewPath": "",
              "visible": true,
              "width": ""
            },
            {
              "align": "center",
              "boolean": "checkbox",
              "dateFormat": "MM/DD/YYYY",
              "editable": false,
              "field": "ProjectDescription",
              "filter": {
                "boolean": {
                  "condition": ""
                },
                "date": {
                  "condition": "",
                  "value": ""
                },
                "enabled": false,
                "number": {
                  "condition": "",
                  "value": ""
                },
                "string": {
                  "condition": "",
                  "value": ""
                },
                "visible": "on-hover"
              },
              "footer": {
                "align": "center",
                "justify": "left",
                "style": {
                  "classes": ""
                },
                "title": ""
              },
              "header": {
                "align": "center",
                "justify": "center",
                "style": {
                  "classes": ""
                },
                "title": "Project Desc."
              },
              "justify": "center",
              "nullFormat": {
                "includeNullStrings": false,
                "nullFormatValue": "",
                "strict": false
              },
              "number": "value",
              "numberFormat": "0,0.##",
              "progressBar": {
                "bar": {
                  "color": "",
                  "style": {
                    "classes": ""
                  }
                },
                "max": 100,
                "min": 0,
                "track": {
                  "color": "",
                  "style": {
                    "classes": ""
                  }
                },
                "value": {
                  "enabled": true,
                  "format": "0,0.##",
                  "justify": "center",
                  "style": {
                    "classes": ""
                  }
                }
              },
              "render": "auto",
              "resizable": true,
              "sort": "none",
              "sortable": false,
              "strictWidth": false,
              "style": {
                "classes": ""
              },
              "toggleSwitch": {
                "color": {
                  "selected": "",
                  "unselected": ""
                }
              },
              "viewParams": {},
              "viewPath": "",
              "visible": true,
              "width": ""
            },
            {
              "align": "center",
              "boolean": "checkbox",
              "dateFormat": "MM/DD/YYYY",
              "editable": false,
              "field": "Duration(min)",
              "filter": {
                "boolean": {
                  "condition": ""
                },
                "date": {
                  "condition": "",
                  "value": ""
                },
                "enabled": false,
                "number": {
                  "condition": "",
                  "value": ""
                },
                "string": {
                  "condition": "",
                  "value": ""
                },
                "visible": "on-hover"
              },
              "footer": {
                "align": "center",
                "justify": "left",
                "style": {
                  "classes": ""
                },
                "title": ""
              },
              "header": {
                "align": "center",
                "justify": "center",
                "style": {
                  "classes": ""
                },
                "title": ""
              },
              "justify": "center",
              "nullFormat": {
                "includeNullStrings": false,
                "nullFormatValue": "",
                "strict": false
              },
              "number": "value",
              "numberFormat": "0,0.##",
              "progressBar": {
                "bar": {
                  "color": "",
                  "style": {
                    "classes": ""
                  }
                },
                "max": 100,
                "min": 0,
                "track": {
                  "color": "",
                  "style": {
                    "classes": ""
                  }
                },
                "value": {
                  "enabled": true,
                  "format": "0,0.##",
                  "justify": "center",
                  "style": {
                    "classes": ""
                  }
                }
              },
              "render": "auto",
              "resizable": true,
              "sort": "none",
              "sortable": false,
              "strictWidth": false,
              "style": {
                "classes": ""
              },
              "toggleSwitch": {
                "color": {
                  "selected": "",
                  "unselected": ""
                }
              },
              "viewParams": {},
              "viewPath": "",
              "visible": true,
              "width": ""
            },
            {
              "align": "center",
              "boolean": "checkbox",
              "dateFormat": "MM/DD/YY hh:mm",
              "editable": false,
              "field": "SDateTime",
              "filter": {
                "boolean": {
                  "condition": ""
                },
                "date": {
                  "condition": "",
                  "value": ""
                },
                "enabled": false,
                "number": {
                  "condition": "",
                  "value": ""
                },
                "string": {
                  "condition": "",
                  "value": ""
                },
                "visible": "on-hover"
              },
              "footer": {
                "align": "center",
                "justify": "left",
                "style": {
                  "classes": ""
                },
                "title": ""
              },
              "header": {
                "align": "center",
                "justify": "center",
                "style": {
                  "classes": ""
                },
                "title": "Project Start"
              },
              "justify": "center",
              "nullFormat": {
                "includeNullStrings": false,
                "nullFormatValue": "",
                "strict": false
              },
              "number": "value",
              "numberFormat": "0,0.##",
              "progressBar": {
                "bar": {
                  "color": "",
                  "style": {
                    "classes": ""
                  }
                },
                "max": 100,
                "min": 0,
                "track": {
                  "color": "",
                  "style": {
                    "classes": ""
                  }
                },
                "value": {
                  "enabled": true,
                  "format": "0,0.##",
                  "justify": "center",
                  "style": {
                    "classes": ""
                  }
                }
              },
              "render": "auto",
              "resizable": true,
              "sort": "none",
              "sortable": false,
              "strictWidth": false,
              "style": {
                "classes": ""
              },
              "toggleSwitch": {
                "color": {
                  "selected": "",
                  "unselected": ""
                }
              },
              "viewParams": {},
              "viewPath": "",
              "visible": true,
              "width": ""
            },
            {
              "align": "center",
              "boolean": "checkbox",
              "dateFormat": "MM/DD/YY hh:mm",
              "editable": false,
              "field": "EDateTime",
              "filter": {
                "boolean": {
                  "condition": ""
                },
                "date": {
                  "condition": "",
                  "value": ""
                },
                "enabled": false,
                "number": {
                  "condition": "",
                  "value": ""
                },
                "string": {
                  "condition": "",
                  "value": ""
                },
                "visible": "on-hover"
              },
              "footer": {
                "align": "center",
                "justify": "left",
                "style": {
                  "classes": ""
                },
                "title": ""
              },
              "header": {
                "align": "center",
                "justify": "center",
                "style": {
                  "classes": ""
                },
                "title": "Project End"
              },
              "justify": "center",
              "nullFormat": {
                "includeNullStrings": false,
                "nullFormatValue": "",
                "strict": false
              },
              "number": "value",
              "numberFormat": "0,0.##",
              "progressBar": {
                "bar": {
                  "color": "",
                  "style": {
                    "classes": ""
                  }
                },
                "max": 100,
                "min": 0,
                "track": {
                  "color": "",
                  "style": {
                    "classes": ""
                  }
                },
                "value": {
                  "enabled": true,
                  "format": "0,0.##",
                  "justify": "center",
                  "style": {
                    "classes": ""
                  }
                }
              },
              "render": "auto",
              "resizable": true,
              "sort": "none",
              "sortable": false,
              "strictWidth": false,
              "style": {
                "classes": ""
              },
              "toggleSwitch": {
                "color": {
                  "selected": "",
                  "unselected": ""
                }
              },
              "viewParams": {},
              "viewPath": "",
              "visible": true,
              "width": ""
            },
            {
              "align": "center",
              "boolean": "checkbox",
              "dateFormat": "MM/DD/YYYY",
              "editable": false,
              "field": "Status",
              "filter": {
                "boolean": {
                  "condition": ""
                },
                "date": {
                  "condition": "",
                  "value": ""
                },
                "enabled": false,
                "number": {
                  "condition": "",
                  "value": ""
                },
                "string": {
                  "condition": "",
                  "value": ""
                },
                "visible": "on-hover"
              },
              "footer": {
                "align": "center",
                "justify": "left",
                "style": {
                  "classes": ""
                },
                "title": ""
              },
              "header": {
                "align": "center",
                "justify": "center",
                "style": {
                  "classes": ""
                },
                "title": ""
              },
              "justify": "center",
              "nullFormat": {
                "includeNullStrings": false,
                "nullFormatValue": "",
                "strict": false
              },
              "number": "value",
              "numberFormat": "0,0.##",
              "progressBar": {
                "bar": {
                  "color": "",
                  "style": {
                    "classes": ""
                  }
                },
                "max": 100,
                "min": 0,
                "track": {
                  "color": "",
                  "style": {
                    "classes": ""
                  }
                },
                "value": {
                  "enabled": true,
                  "format": "0,0.##",
                  "justify": "center",
                  "style": {
                    "classes": ""
                  }
                }
              },
              "render": "auto",
              "resizable": true,
              "sort": "none",
              "sortable": false,
              "strictWidth": false,
              "style": {
                "classes": ""
              },
              "toggleSwitch": {
                "color": {
                  "selected": "",
                  "unselected": ""
                }
              },
              "viewParams": {},
              "viewPath": "",
              "visible": true,
              "width": ""
            },
            {
              "align": "center",
              "boolean": "checkbox",
              "dateFormat": "MM/DD/YYYY",
              "editable": false,
              "field": "ProjectOwner",
              "filter": {
                "boolean": {
                  "condition": ""
                },
                "date": {
                  "condition": "",
                  "value": ""
                },
                "enabled": false,
                "number": {
                  "condition": "",
                  "value": ""
                },
                "string": {
                  "condition": "",
                  "value": ""
                },
                "visible": "on-hover"
              },
              "footer": {
                "align": "center",
                "justify": "left",
                "style": {
                  "classes": ""
                },
                "title": ""
              },
              "header": {
                "align": "center",
                "justify": "center",
                "style": {
                  "classes": ""
                },
                "title": "Project Owner"
              },
              "justify": "center",
              "nullFormat": {
                "includeNullStrings": false,
                "nullFormatValue": "",
                "strict": false
              },
              "number": "value",
              "numberFormat": "0,0.##",
              "progressBar": {
                "bar": {
                  "color": "",
                  "style": {
                    "classes": ""
                  }
                },
                "max": 100,
                "min": 0,
                "track": {
                  "color": "",
                  "style": {
                    "classes": ""
                  }
                },
                "value": {
                  "enabled": true,
                  "format": "0,0.##",
                  "justify": "center",
                  "style": {
                    "classes": ""
                  }
                }
              },
              "render": "auto",
              "resizable": true,
              "sort": "none",
              "sortable": false,
              "strictWidth": false,
              "style": {
                "classes": ""
              },
              "toggleSwitch": {
                "color": {
                  "selected": "",
                  "unselected": ""
                }
              },
              "viewParams": {},
              "viewPath": "",
              "visible": true,
              "width": ""
            },
            {
              "align": "center",
              "boolean": "checkbox",
              "dateFormat": "MM/DD/YYYY",
              "editable": true,
              "field": "Remark",
              "filter": {
                "boolean": {
                  "condition": ""
                },
                "date": {
                  "condition": "",
                  "value": ""
                },
                "enabled": false,
                "number": {
                  "condition": "",
                  "value": ""
                },
                "string": {
                  "condition": "",
                  "value": ""
                },
                "visible": "on-hover"
              },
              "footer": {
                "align": "center",
                "justify": "left",
                "style": {
                  "classes": ""
                },
                "title": ""
              },
              "header": {
                "align": "center",
                "justify": "center",
                "style": {
                  "classes": ""
                },
                "title": ""
              },
              "justify": "center",
              "nullFormat": {
                "includeNullStrings": false,
                "nullFormatValue": "",
                "strict": false
              },
              "number": "value",
              "numberFormat": "0,0.##",
              "progressBar": {
                "bar": {
                  "color": "",
                  "style": {
                    "classes": ""
                  }
                },
                "max": 100,
                "min": 0,
                "track": {
                  "color": "",
                  "style": {
                    "classes": ""
                  }
                },
                "value": {
                  "enabled": true,
                  "format": "0,0.##",
                  "justify": "center",
                  "style": {
                    "classes": ""
                  }
                }
              },
              "render": "auto",
              "resizable": true,
              "sort": "none",
              "sortable": false,
              "strictWidth": false,
              "style": {
                "classes": ""
              },
              "toggleSwitch": {
                "color": {
                  "selected": "",
                  "unselected": ""
                }
              },
              "viewParams": {},
              "viewPath": "",
              "width": ""
            }
          ],
          "filter": {
            "enabled": true
          },
          "pager": {
            "activeOption": 7,
            "bottom": false,
            "options": [
              7,
              10,
              25,
              50,
              100
            ]
          },
          "selection": {
            "mode": "multiple interval"
          },
          "style": {
            "borderTopLeftRadius": 10,
            "borderTopRightRadius": 10,
            "outlineStyle": "solid",
            "paddingLeft": 2,
            "paddingRight": 2,
            "paddingTop": 2
          }
        },
        "type": "ia.display.table"
      },
      {
        "events": {
          "dom": {
            "onClick": [
              {
                "config": {
                  "script": "\tnamedQuery \u003d \"joinEmpReq\"\n#\tparameters \u003d {\"RID\": self.getSibling(\"ReqTable\").props.selection.data[0].RID}\n \tsystem.db.runNamedQuery(namedQuery)\n# \tnq \u003d \"ApproveQuery\"\n# \tsystem.db.runNamedQuery(nq)\n# \tsystem.perspective.openPopup(\"myID3\", \u0027Approved\u0027)"
                },
                "scope": "G",
                "type": "script"
              },
              {
                "config": {
                  "script": "\tself.getSibling(\"EquipmentSchedule\").refreshBinding(\"props.data\")\n#\tself.getSibling(\"Table\").refreshBinding(\"props.data\")\n#\tself.getSibling(\"ReqTable\").refreshBinding(\"props.data\")"
                },
                "scope": "G",
                "type": "script"
              },
              {
                "config": {
                  "draggable": false,
                  "id": "A2TQ4yW6",
                  "modal": false,
                  "overlayDismiss": true,
                  "resizable": true,
                  "showCloseIcon": false,
                  "type": "open",
                  "viewPath": "Approved",
                  "viewportBound": false
                },
                "scope": "C",
                "type": "popup"
              }
            ]
          }
        },
        "meta": {
          "name": "Approve"
        },
        "position": {
          "height": 0.0483,
          "width": 0.1117,
          "x": 0.3539,
          "y": 0.4981
        },
        "propConfig": {
          "props.enabled": {
            "binding": {
              "config": {
                "expression": "if({session.props.auth.user.roles[0]} \u003d \u0027Administrator\u0027,true,false)"
              },
              "type": "expr"
            }
          }
        },
        "props": {
          "text": "Approve",
          "textStyle": {
            "fontSize": 15
          }
        },
        "type": "ia.input.button"
      },
      {
        "meta": {
          "name": "Label_0"
        },
        "position": {
          "height": 0.04,
          "width": 0.3582,
          "x": 0.025,
          "y": 0.5054
        },
        "props": {
          "style": {
            "color": "#00AC00",
            "fontFamily": "serif",
            "fontSize": 20,
            "fontStyle": "italic",
            "fontWeight": "bold"
          },
          "text": "Admin approval needed for these Schedules..."
        },
        "type": "ia.display.label"
      },
      {
        "events": {
          "dom": {
            "onClick": [
              {
                "config": {
                  "script": "#\tnamedQuery \u003d \"Reject\"\n#\tparameters \u003d {\"RID\": self.getSibling(\"ReqTable\").props.selection.data[0].RID}\n#\tsystem.db.runNamedQuery(namedQuery, parameters)\n#\tsystem.perspective.openPopup(\"myID4\", \u0027Rejectedpopup\u0027)\n\tnamedQuery \u003d \"Reject\"\n\tselectedRows \u003d self.getSibling(\"ReqTable\").props.selection.data\n\t\n\tfor row in selectedRows:\n\t    parameters \u003d {\"RID\": row[\"RID\"]}\n\t    system.db.runNamedQuery(namedQuery, parameters)\n\t\n#\tsystem.perspective.openPopup(\"myID4\", \u0027Rejectedpopup\u0027)"
                },
                "scope": "G",
                "type": "script"
              },
              {
                "config": {
                  "script": "\tself.getSibling(\"EquipmentSchedule\").refreshBinding(\"props.data\")"
                },
                "scope": "G",
                "type": "script"
              },
              {
                "config": {
                  "draggable": false,
                  "id": "pp685a9O",
                  "modal": false,
                  "overlayDismiss": true,
                  "resizable": true,
                  "showCloseIcon": false,
                  "type": "open",
                  "viewPath": "Rejectedpopup",
                  "viewportBound": false
                },
                "scope": "C",
                "type": "popup"
              }
            ]
          }
        },
        "meta": {
          "name": "Reject"
        },
        "position": {
          "height": 0.0483,
          "width": 0.1117,
          "x": 0.4895,
          "y": 0.4981
        },
        "propConfig": {
          "props.enabled": {
            "binding": {
              "config": {
                "expression": "if({session.props.auth.user.roles[0]}\u003d \u0027Administrator\u0027,true,false)"
              },
              "type": "expr"
            }
          }
        },
        "props": {
          "text": "Reject",
          "textStyle": {
            "fontSize": 15
          }
        },
        "type": "ia.input.button"
      },
      {
        "events": {
          "component": {
            "onDeleteEvent": {
              "config": {
                "script": "\t\t# Get the list of scheduled events\n\tscheduled \u003d self.props.scheduledEvents\n\t\n\t# Get the ID of the event to delete\n\tevent_id \u003d event.eventId\n\titem_id \u003d event.itemId\n\t\n\t# Run the Named Query to update and delete from the database\n\tparams \u003d {\"eventId\": event_id}\n#\tsystem.db.runNamedQuery(\"UpdateRequestStatus\", params)  # Named Query: update Request set Status \u003d \u0027Slot Not Available\u0027 where RID \u003d :eventId\n\tsystem.db.runNamedQuery(\"DeleteSchedule\", params)       # Named Query: delete from Schedules where eventId \u003d :eventId\n\t\n\t# Remove the event from the component\u0027s props\n\tself.props.scheduledEvents \u003d [e for e in scheduled if not (e[\u0027eventId\u0027] \u003d\u003d event_id and e[\u0027itemId\u0027] \u003d\u003d item_id)]"
              },
              "scope": "G",
              "type": "script"
            },
            "onResizeEvent": {
              "config": {
                "script": "\teventId \u003d self.props.selectedEvent.eventId\n\titemId \u003d self.props.selectedEvent.itemId\n\tquery \u003d \"SELECT startDate, endDate FROM Schedules WHERE eventId \u003d ?\"\n\teventData \u003d system.db.runPrepQuery(query, [eventId])[0]\n\toriginalStartDate \u003d eventData[\u0027startDate\u0027]\n\toriginalEndDate \u003d eventData[\u0027endDate\u0027]\n\tqq \u003d \"SELECT (20 * 60) - (DATEPART(HOUR, ?) * 60 + DATEPART(MINUTE, ?)) AS DurationInMinutes\"\n\tresult \u003d system.db.runPrepQuery(qq, [eventData[\u0027endDate\u0027], eventData[\u0027endDate\u0027]])\n\tremainingMinutes \u003d result[0][\u0027DurationInMinutes\u0027]\n\tbreakStartHour \u003d 20  # 8 PM\n\tbreakEndHour \u003d 8     # 8 AM next day\n\tif remainingMinutes \u003e\u003d 60:\n\t\tnewStartDate \u003d originalStartDate\n\t\tnewEndDate \u003d system.date.addMinutes(originalEndDate, 60)\n\t\tupdateMain \u003d \"UPDATE Schedules SET startDate \u003d ?, endDate \u003d ? WHERE eventId \u003d ?\"\n\t\tsystem.db.runPrepUpdate(updateMain, [newStartDate, newEndDate, eventId])\n\t\tupdateRequest \u003d \"UPDATE Request SET SDateTime \u003d ?, EDateTime \u003d ? WHERE RID \u003d ?\"\n\t\tsystem.db.runPrepUpdate(updateRequest, [newStartDate, newEndDate, eventId])\n\t\tcurrentEnd \u003d newEndDate\n\telse:\n\t\tupdatedate \u003d system.date.addDays(originalStartDate, 1)\n\t\tupdatetime \u003d system.date.setTime(updatedate, 7, 0, 0)\n\t\tl \u003d \"SELECT eventId AS next FROM Schedules WHERE itemId \u003d ? AND startDate \u003d ?\"\n\t\tll \u003d system.db.runPrepQuery(l, [itemId,updatetime])\n\t\tif ll.getRowCount() \u003e 0:\n\t\t\tlll \u003d ll.getValueAt(0, \"next\")  # ✅ Safe access\n\t\telse:\n\t\t\tlll \u003d None  # Or handle gracefully\n#\t\tlll \u003d ll[0]\n\t\tif lll is None:\n\t\t\tproposedEndDate \u003d system.date.addMinutes(originalEndDate, 60)\n\t\t\tbreakStart \u003d system.date.setTime(originalEndDate, breakStartHour, 0, 0)\n\t\t\tfirstPartEnd \u003d breakStart\n\t\t\tremainingDuration \u003d system.date.minutesBetween(breakStart, proposedEndDate)\n\t\t\tsystem.db.runPrepUpdate(\"UPDATE Schedules SET startDate \u003d ?, endDate \u003d ? WHERE eventId \u003d ?\", [originalStartDate, firstPartEnd, eventId])\n\t\t\tsystem.db.runPrepUpdate(\"UPDATE Request SET SDateTime \u003d ?, EDateTime \u003d ? WHERE RID \u003d ?\", [originalStartDate, firstPartEnd, eventId])\n\t\t\tnextDayStart \u003d system.date.addDays(originalStartDate, 1)\n\t\t\tnextDayStartt \u003d system.date.setTime(nextDayStart, breakEndHour-1, 0, 0)\n\t\t\tsecondPartEnd \u003d system.date.addMinutes(nextDayStartt, remainingDuration)\n\t\t\tqueryTasksyyy \u003d \"SELECT RID, Department,Status,l,RequestTime,ProjectDescription,ProjectOwner,Remark FROM Request WHERE RID \u003d ?\"\n\t\t\ttaskrow \u003d system.db.runPrepQuery(queryTasksyyy, [eventId])\n\t\t\ttasksyyy \u003d taskrow[0]\n\t\t\tinsertQuery1 \u003d \"INSERT INTO Request (Department,SDateTime, EDateTime, Status, l,RequestTime,ProjectDescription,ProjectOwner,Remark,SubID) VALUES (?, ?, ?, ?,?,?,?,?,?,?)\"\n\t\t\tsystem.db.runPrepUpdate(insertQuery1, [tasksyyy[\u0027Department\u0027], nextDayStartt, secondPartEnd, tasksyyy[\u0027Status\u0027],tasksyyy[\u0027l\u0027],tasksyyy[\u0027RequestTime\u0027],tasksyyy[\u0027ProjectDescription\u0027],tasksyyy[\u0027ProjectOwner\u0027],tasksyyy[\u0027Remark\u0027],tasksyyy[\u0027RID\u0027]])\n\t\t\tmaxx \u003d \"SELECT EDateTime FROM Request WHERE RID \u003d (SELECT MAX(RID) FROM Request)\"\n\t\t\tmaxxrow \u003d system.db.runPrepQuery(maxx)\n\t\t\tmaxxans \u003d maxxrow.getValueAt(0,\"EDateTime\")\n\t\t\tm \u003d \"SELECT DATEPART(MINUTE, ?) AS m\"\n\t\t\tmm \u003d system.db.runPrepQuery(m,[maxxans])\n\t\t\tmmm \u003d mm[0][\u0027m\u0027]\n\t\t\tnamedQuery \u003d \"INSERT INTO Schedules SELECT E.ID AS itemId, R.RID AS eventId, R.SDateTime AS startDate, R.EDateTime AS endDate, R.ProjectDescription AS label, R.l AS leadTime FROM Department AS E join Request AS R ON E.Department\u003dR.Department WHERE R.RID NOT IN (SELECT eventId FROM Schedules) AND not (R.Status \u003d \u0027Slot Not Available\u0027)\"\n\t\t\tsystem.db.runPrepUpdate(namedQuery)\n\t\t\tminn \u003d \"SELECT startDate, endDate FROM Schedules WHERE eventId \u003d (SELECT MAX(eventId) FROM Schedules)\"\n\t\t\tminnrow \u003d system.db.runPrepQuery(minn)\n\t\t\tst \u003d minnrow[0][\u0027startDate\u0027]\n\t\t\ten \u003d minnrow[0][\u0027endDate\u0027]\n\t\t\tif mmm \u003d\u003d 30:\n\t\t\t\taddddstart \u003d system.date.addMinutes(st, -30)\n\t\t\t\taddddend \u003d system.date.addMinutes(en, -30)\n\t\t\telse:\n\t\t\t\taddddstart \u003d system.date.addMinutes(st, -60)\n\t\t\t\taddddend \u003d system.date.addMinutes(en, -60)\n\t\t\tnow \u003d \"UPDATE Schedules SET startDate \u003d ?, endDate \u003d ? WHERE eventId \u003d (SELECT MAX(eventId) FROM Schedules)\"\n\t\t\tsystem.db.runPrepUpdate(now,[addddstart,addddend])\n\t\t\tcurrentEnd \u003d secondPartEnd\n\t\telse:\n\t\t\tz \u003d \"SELECT RID, SubID, Status FROM Request WHERE RID \u003d ?\"\n\t\t\tzz \u003d system.db.runPrepQuery(z, [lll])\n\t\t\tzzz \u003d zz[0]\n\t\t\tRID \u003d zzz[\u0027RID\u0027]\n\t\t\tif zzz[\u0027SubID\u0027] \u003d\u003d 0:\n\t\t\t\tproposedEndDate \u003d system.date.addMinutes(originalEndDate, 60)\n\t\t\t\tbreakStart \u003d system.date.setTime(originalEndDate, breakStartHour, 0, 0)\n\t\t\t\tfirstPartEnd \u003d breakStart\n\t\t\t\tremainingDuration \u003d system.date.minutesBetween(breakStart, proposedEndDate)\n\t\t\t\tsystem.db.runPrepUpdate(\"UPDATE Schedules SET startDate \u003d ?, endDate \u003d ? WHERE eventId \u003d ?\", [originalStartDate, firstPartEnd, eventId])\n\t\t\t\tsystem.db.runPrepUpdate(\"UPDATE Request SET SDateTime \u003d ?, EDateTime \u003d ? WHERE RID \u003d ?\", [originalStartDate, firstPartEnd, eventId])\n\t\t\t\tnextDayStart \u003d system.date.addDays(originalStartDate, 1)\n\t\t\t\tnextDayStartt \u003d system.date.setTime(nextDayStart, breakEndHour-1, 0, 0)\n\t\t\t\tsecondPartEnd \u003d system.date.addMinutes(nextDayStartt, remainingDuration)\n\t\t\t\tqueryTasksyyy \u003d \"SELECT RID,Department,Status,l,RequestTime,ProjectDescription,ProjectOwner,Remark FROM Request WHERE RID \u003d ?\"\n\t\t\t\ttaskrow \u003d system.db.runPrepQuery(queryTasksyyy, [eventId])\n\t\t\t\ttasksyyy \u003d taskrow[0]\n\t\t\t\tinsertQuery1 \u003d \"INSERT INTO Request (Department,SDateTime, EDateTime, Status, l,RequestTime,ProjectDescription,ProjectOwner,Remark,SubID) VALUES (?, ?, ?, ?,?,?,?,?,?,?)\"\n\t\t\t\tsystem.db.runPrepUpdate(insertQuery1, [tasksyyy[\u0027Department\u0027], nextDayStartt, secondPartEnd, tasksyyy[\u0027Status\u0027],tasksyyy[\u0027l\u0027],tasksyyy[\u0027RequestTime\u0027],tasksyyy[\u0027ProjectDescription\u0027],tasksyyy[\u0027ProjectOwner\u0027],tasksyyy[\u0027Remark\u0027],tasksyyy[\u0027RID\u0027]])\n\t\t\t\tmaxx \u003d \"SELECT EDateTime FROM Request WHERE RID \u003d (SELECT MAX(RID) FROM Request)\"\n\t\t\t\tmaxxrow \u003d system.db.runPrepQuery(maxx)\n\t\t\t\tmaxxans \u003d maxxrow.getValueAt(0,\"EDateTime\")\n\t\t\t\tm \u003d \"SELECT DATEPART(MINUTE, ?) AS m\"\n\t\t\t\tmm \u003d system.db.runPrepQuery(m,[maxxans])\n\t\t\t\tmmm \u003d mm[0][\u0027m\u0027]\n\t\t\t\tnamedQuery \u003d \"INSERT INTO Schedules SELECT E.ID AS itemId, R.RID AS eventId, R.SDateTime AS startDate, R.EDateTime AS endDate, R.ProjectDescription AS label, R.l AS leadTime FROM Department AS E join Request AS R ON E.Department\u003dR.Department WHERE R.RID NOT IN (SELECT eventId FROM Schedules) AND not (R.Status \u003d \u0027Slot Not Available\u0027)\"\n\t\t\t\tsystem.db.runPrepUpdate(namedQuery)\n\t\t\t\tminn \u003d \"SELECT startDate, endDate FROM Schedules WHERE eventId \u003d (SELECT MAX(eventId) FROM Schedules)\"\n\t\t\t\tminnrow \u003d system.db.runPrepQuery(minn)\n\t\t\t\tst \u003d minnrow[0][\u0027startDate\u0027]\n\t\t\t\ten \u003d minnrow[0][\u0027endDate\u0027]\n\t\t\t\tif mmm \u003d\u003d 30:\n\t\t\t\t\taddddstart \u003d system.date.addMinutes(st, -30)\n\t\t\t\t\taddddend \u003d system.date.addMinutes(en, -30)\n\t\t\t\telse:\n\t\t\t\t\taddddstart \u003d system.date.addMinutes(st, -60)\n\t\t\t\t\taddddend \u003d system.date.addMinutes(en, -60)\n\t\t\t\tnow \u003d \"UPDATE Schedules SET startDate \u003d ?, endDate \u003d ? WHERE eventId \u003d (SELECT MAX(eventId) FROM Schedules)\"\n\t\t\t\tsystem.db.runPrepUpdate(now,[addddstart,addddend])\n\t\t\t\tcurrentEnd \u003d secondPartEnd\n\t\t\telse:\n\t\t\t\tquery \u003d \"SELECT startDate, endDate FROM Schedules WHERE eventId \u003d ?\"\n\t\t\t\tnextdata \u003d system.db.runPrepQuery(query, [RID])[0]\n\t\t\t\tNextStartDate \u003d nextdata[\u0027startDate\u0027]\n\t\t\t\tNextEndDate \u003d nextdata[\u0027endDate\u0027]\n\t\t\t\tNextProposedEndDate \u003d system.date.addMinutes(NextEndDate, 60)\n\t\t\t\tsystem.db.runPrepUpdate(\"UPDATE Schedules SET startDate \u003d ?, endDate \u003d ? WHERE eventId \u003d ?\", [NextStartDate, NextEndDate, RID])\n\t\t\t\tsystem.db.runPrepUpdate(\"UPDATE Request SET SDateTime \u003d ?, EDateTime \u003d ? WHERE RID \u003d ?\", [NextStartDate, NextEndDate, RID])\n\t\t\t\tcurrentEnd \u003d NextEndDate\n\tqueryTasks \u003d \"\"\"SELECT itemId, eventId, startDate, endDate, label\n\tFROM Schedules\n\tWHERE itemId \u003d ? AND eventId !\u003d ? AND startDate \u003e ?\n\tORDER BY startDate\"\"\"\n\ttasks \u003d system.db.runPrepQuery(queryTasks, [itemId, eventId, originalStartDate])\n\tfor task in tasks:\n\t\tif task[\u0027startDate\u0027] \u003c currentEnd:\n\t\t\tduration \u003d system.date.minutesBetween(task[\u0027startDate\u0027], task[\u0027endDate\u0027])\n\t\t\tnewStart \u003d currentEnd\n\t\t\tnewEnd \u003d system.date.addMinutes(newStart, duration)\n\t\t\tbreakStart \u003d system.date.setTime(newStart, breakStartHour, 0, 0)\n\t\t\tbreakEndd \u003d system.date.addDays(breakStart, 1)\n\t\t\tbreakEnd \u003d system.date.setTime(breakEndd, breakEndHour, 0, 0)\n\t\t\tif newEnd \u003e breakStart:\n\t\t\t\tproposedEndDate1 \u003d newEnd\n\t\t\t\tfirstPartEnd1 \u003d breakStart\n\t\t\t\tremainingDuration1 \u003d system.date.minutesBetween(breakStart, proposedEndDate1)\n\t\t\t\tsystem.db.runPrepUpdate(\"UPDATE Schedules SET startDate \u003d ?, endDate \u003d ? WHERE eventId \u003d ?\", [newStart, firstPartEnd1, task[\u0027eventId\u0027]])\n\t\t\t\tsystem.db.runPrepUpdate(\"UPDATE Request SET SDateTime \u003d ?, EDateTime \u003d ? WHERE RID \u003d ?\", [newStart, firstPartEnd1, task[\u0027eventId\u0027]])\n\t\t\t\tnextDayStart \u003d system.date.addDays(newStart, 1)\n\t\t\t\tnextDayStartt \u003d system.date.setTime(nextDayStart, breakEndHour+1, 0, 0)\n\t\t\t\tsecondPartEnd1 \u003d system.date.addMinutes(nextDayStartt, remainingDuration1)\n\t\t\t\tqueryTasksxxx \u003d \"SELECT Department,Status,l,RequestTime,ProjectDescription,ProjectOwner,Remark FROM Request WHERE RID \u003d ?\"\n\t\t\t\ttasksrow1 \u003d system.db.runPrepQuery(queryTasksxxx, [task[\u0027eventId\u0027]])\n\t\t\t\ttasksxxx \u003d tasksrow1[0]\n\t\t\t\tinsertQuery12 \u003d \"INSERT INTO Request (Department,SDateTime, EDateTime, Status, l,RequestTime,ProjectDescription,ProjectOwner,Remark) VALUES (?, ?, ?, ?,?,?,?,?,?)\"\n\t\t\t\tsystem.db.runPrepUpdate(insertQuery12, [tasksxxx[\u0027Department\u0027], nextDayStartt, secondPartEnd1, tasksxxx[\u0027Status\u0027],tasksxxx[\u0027l\u0027],tasksxxx[\u0027RequestTime\u0027],tasksxxx[\u0027ProjectDescription\u0027],tasksxxx[\u0027ProjectOwner\u0027],tasksxxx[\u0027Remark\u0027]])\n\t\t\t\tmaxx \u003d \"SELECT EDateTime FROM Request WHERE RID \u003d (SELECT MAX(RID) FROM Request)\"\n\t\t\t\tmaxxrow \u003d system.db.runPrepQuery(maxx)\n\t\t\t\tmaxxans \u003d maxxrow.getValueAt(0,\"EDateTime\")\n\t\t\t\tm \u003d \"SELECT DATEPART(MINUTE, ?) AS m\"\n\t\t\t\tmm \u003d system.db.runPrepQuery(m,[maxxans])\n\t\t\t\tmmm \u003d mm[0][\u0027m\u0027]\n\t\t\t\tnamedQuery \u003d \"INSERT INTO Schedules SELECT E.ID AS itemId, R.RID AS eventId, R.SDateTime AS startDate, R.EDateTime AS endDate, R.ProjectDescription AS label, R.l AS leadTime FROM Department AS E join Request AS R ON E.Department\u003dR.Department WHERE R.RID NOT IN (SELECT eventId FROM Schedules) AND not (R.Status \u003d \u0027Slot Not Available\u0027)\"\n\t\t\t\tsystem.db.runPrepUpdate(namedQuery)\n\t\t\t\tminn \u003d \"SELECT eventId, startDate, endDate FROM Schedules WHERE eventId \u003d (SELECT MAX(eventId) FROM Schedules)\"\n\t\t\t\tminnrow \u003d system.db.runPrepQuery(minn)\n\t\t\t\tst \u003d minnrow[0][\u0027startDate\u0027]\n\t\t\t\ten \u003d minnrow[0][\u0027endDate\u0027]\n\t\t\t\tei \u003d minnrow[0][\u0027eventId\u0027]\n\t\t\t\tif mmm \u003d\u003d 30:\n\t\t\t\t\taddddstart \u003d system.date.addMinutes(st, -30)\n\t\t\t\t\taddddend \u003d system.date.addMinutes(en, -30)\n\t\t\t\telse:\n\t\t\t\t\taddddstart \u003d system.date.addMinutes(st, -60)\n\t\t\t\t\taddddend \u003d system.date.addMinutes(en, -60)\n\t\t\t\tnow \u003d \"UPDATE Schedules SET startDate \u003d ?, endDate \u003d ? WHERE eventId \u003d (SELECT MAX(eventId) FROM Schedules)\"\n\t\t\t\tsystem.db.runPrepUpdate(now,[addddstart,addddend])\n#\t\t\t\tnamedQuery1 \u003d \"INSERT INTO Schedules SELECT E.ID AS itemId, R.RID AS eventId, R.SDateTime AS startDate, R.EDateTime AS endDate, R.ProjectDescription AS label, R.l AS leadTime FROM Department AS E join Request AS R ON E.Department\u003dR.Department WHERE R.RID NOT IN (SELECT eventId FROM Schedules) AND not (R.Status \u003d \u0027Slot Not Available\u0027)\"\n#\t\t\t\tsystem.db.runPrepUpdate(namedQuery1)\n\t\t\t\tcurrentEnd \u003d addddend\n\t\t\t\tqueryTasks \u003d \"\"\"SELECT itemId, eventId, startDate, endDate, label\n\t\t\t\tFROM Schedules\n\t\t\t\tWHERE itemId \u003d ? AND eventId NOT IN (?,?) AND startDate \u003e\u003d ?\n\t\t\t\tORDER BY startDate\"\"\"\n\t\t\t\ttasks \u003d system.db.runPrepQuery(queryTasks, [itemId, eventId, ei, addddstart])\n\t\t\telse:\n\t\t\t\tupdateTask \u003d \"UPDATE Schedules SET startDate \u003d ?, endDate \u003d ? WHERE eventId \u003d ?\"\n\t\t\t\tsystem.db.runPrepUpdate(updateTask, [newStart, newEnd, task[\u0027eventId\u0027]])\n\t\t\t\tupdateRequest \u003d \"UPDATE Request SET SDateTime \u003d ?, EDateTime \u003d ? WHERE RID \u003d ?\"\n\t\t\t\tsystem.db.runPrepUpdate(updateRequest, [newStart, newEnd, task[\u0027eventId\u0027]])\n\t\t\t\tcurrentEnd \u003d newEnd\n\t\telse:\n\t\t\tpass"
              },
              "scope": "G",
              "type": "script"
            }
          },
          "dom": {
            "onClick": {
              "config": {
                "script": "\t\t# Get current state\n\tsystem.perspective.closePopup(\u0027SXfGZFK0\u0027)\n\tif self.session.custom.swap \u003d\u003d 1:\n\t\teventState \u003d self.session.custom.task1\n\t\tclickedId \u003d self.props.selectedEvent[\u0027eventId\u0027]  # Assuming \u0027event\u0027 is the clicked event object\n\t\tself.session.custom.item \u003d self.props.selectedEvent[\u0027itemId\u0027]\n\t\t# Update click count and store IDs\n\t\tif eventState[\u0027clickCount\u0027] \u003d\u003d 0:\n\t\t    self.session.custom.task1 \u003d {\n\t\t        \"firstId\": clickedId,\n\t\t        \"secondId\": None,\n\t\t        \"clickCount\": 1\n\t\t    }\n\t\telif eventState[\u0027clickCount\u0027] \u003d\u003d 1:\n\t\t    self.session.custom.task1 \u003d {\n\t\t        \"firstId\": eventState[\u0027firstId\u0027],\n\t\t        \"secondId\": clickedId,\n\t\t        \"clickCount\": 2\n\t\t    }\n\t\t    self.session.custom.swap\u003d0\n\t\t    system.perspective.openPopup(id\u003d\"abc123\", view\u003d\"SwapPopupConfirm\")\n\t\telse:\n\t\t    # Reset after 2 clicks\n\t\t    self.session.custom.task1 \u003d {\n\t\t        \"firstId\": None,\n\t\t        \"secondId\": None,\n\t\t        \"clickCount\": 0\n\t\t    }\n\t\t    self.session.custom.swap\u003d0\n\telse:\n\t\tpass"
              },
              "scope": "G",
              "type": "script"
            },
            "onDoubleClick": {
              "config": {
                "script": "\t# Get swap parameter\n\tswap \u003d self.session.custom.swap\n\t\n\t# Get selected task details\n\teventId \u003d self.props.selectedEvent.eventId  # This is an array of selected tasks\n\tif swap \u003d\u003d 0:\n\t\tsystem.perspective.openPopup(\n\t\tid\u003d\"yiKlMo63\",\n\t\tview\u003d\"Detailspopup\",\n\t\tparams\u003d{\"eventId\": eventId})"
              },
              "scope": "G",
              "type": "script"
            },
            "onSelect": {
              "config": {
                "script": "\t\t# Assume you have the IDs of the two tasks to swap\n\ttask1_id \u003d self.props.selectedEvent.eventId\n\ttask2_id \u003d self.props.selectedEvent.eventId\n\t\n\t# Step 1: Fetch startDate and endDate of both tasks\n\tquery \u003d \"SELECT eventId, startDate, endDate FROM Schedules WHERE eventId IN (?, ?)\"\n\ttasks \u003d system.db.runPrepQuery(query, [task1_id, task2_id])\n\t\n\tif len(tasks) !\u003d 2:\n\t    system.perspective.print(\"Error: One or both tasks not found.\")\n\telse:\n\t    # Extract task data\n\t    task1 \u003d tasks[0] if tasks[0][\u0027eventId\u0027] \u003d\u003d task1_id else tasks[1]\n\t    task2 \u003d tasks[1] if tasks[0][\u0027eventId\u0027] \u003d\u003d task1_id else tasks[0]\n\t\n\t    # Calculate durations\n\t    duration1 \u003d system.date.getTime(task1[\u0027endDate\u0027]) - system.date.getTime(task1[\u0027startDate\u0027])\n\t    duration2 \u003d system.date.getTime(task2[\u0027endDate\u0027]) - system.date.getTime(task2[\u0027startDate\u0027])\n\t\n\t    # Swap startDates\n\t    newStart1 \u003d task2[\u0027startDate\u0027]\n\t    newStart2 \u003d task1[\u0027startDate\u0027]\n\t\n\t    # Calculate new endDates\n\t    newEnd1 \u003d system.date.addMillis(newStart1, duration1)\n\t    newEnd2 \u003d system.date.addMillis(newStart2, duration2)\n\t\n\t    # Step 2: Update both tasks in the database\n\t    updateQuery \u003d \"UPDATE Schedules SET startDate \u003d ?, endDate \u003d ? WHERE eventId \u003d ?\"\n\t    system.db.runPrepUpdate(updateQuery, [newStart1, newEnd1, task1_id])\n\t    system.db.runPrepUpdate(updateQuery, [newStart2, newEnd2, task2_id])"
              },
              "scope": "G",
              "type": "script"
            }
          }
        },
        "meta": {
          "name": "EquipmentSchedule"
        },
        "position": {
          "height": 0.4767,
          "width": 0.9837,
          "x": 0.0062,
          "y": 0.008
        },
        "propConfig": {
          "props.dateRange.endDate": {
            "binding": {
              "config": {
                "expression": "addDays(now(),20)"
              },
              "type": "expr"
            }
          },
          "props.dateRange.startDate": {
            "binding": {
              "config": {
                "expression": "now()"
              },
              "transforms": [
                {
                  "code": "\tfrom java.util import Calendar\n\tcal \u003d Calendar.getInstance()\n\tcal.set(Calendar.HOUR_OF_DAY,6)\n\tcal.set(Calendar.MINUTE,0)\n\tcal.set(Calendar.SECOND,0)\n\tcal.set(Calendar.MILLISECOND,0)\n\treturn cal.getTime()",
                  "type": "script"
                }
              ],
              "type": "expr"
            }
          },
          "props.deleteEnabled": {
            "binding": {
              "config": {
                "expression": "if({session.props.auth.user.roles[0]} \u003d \u0027Administrator\u0027,true,false)"
              },
              "type": "expr"
            }
          },
          "props.downtimeEvents": {
            "binding": {
              "config": {
                "expression": "now()"
              },
              "transforms": [
                {
                  "code": "\tfrom java.util import Calendar\n\tfrom java.util import ArrayList, HashMap\n\t\n\t# Configuration\n\tnumDays \u003d 22  # Number of future days to repeat\n\t\n\t# Fetch item IDs dynamically from database\n\tquery \u003d \"SELECT ID FROM Department\"\n\titems \u003d [row[\u0027ID\u0027] for row in system.db.runQuery(query)]\n\t\n\t# Result list\n\tevents \u003d ArrayList()\n\t\n\tfor itemId in items:\n\t    # Add today\u0027s early morning downtime (from yesterday 18:30 to today 07:30)\n\t    startCal \u003d Calendar.getInstance()\n\t    startCal.add(Calendar.DATE, -1)\n\t    startCal.set(Calendar.HOUR_OF_DAY, 20)\n\t    startCal.set(Calendar.MINUTE, 0)\n\t    startCal.set(Calendar.SECOND, 0)\n\t    startCal.set(Calendar.MILLISECOND, 0)\n\t    start \u003d startCal.getTime()\n\t\n\t    endCal \u003d Calendar.getInstance()\n\t    endCal.set(Calendar.HOUR_OF_DAY, 8)\n\t    endCal.set(Calendar.MINUTE, 0)\n\t    endCal.set(Calendar.SECOND, 0)\n\t    endCal.set(Calendar.MILLISECOND, 0)\n\t    end \u003d endCal.getTime()\n\t\n\t    event \u003d HashMap()\n\t    event[\"itemId\"] \u003d itemId\n\t    event[\"startDate\"] \u003d start\n\t    event[\"endDate\"] \u003d end\n\t    events.add(event)\n\t\n\t    # Add future 7 days of downtime\n\t    for i in range(numDays):\n\t        startCal \u003d Calendar.getInstance()\n\t        startCal.add(Calendar.DATE, i)\n\t        startCal.set(Calendar.HOUR_OF_DAY, 20)\n\t        startCal.set(Calendar.MINUTE, 0)\n\t        startCal.set(Calendar.SECOND, 0)\n\t        startCal.set(Calendar.MILLISECOND, 0)\n\t        start \u003d startCal.getTime()\n\t\n\t        endCal \u003d Calendar.getInstance()\n\t        endCal.add(Calendar.DATE, i + 1)\n\t        endCal.set(Calendar.HOUR_OF_DAY, 8)\n\t        endCal.set(Calendar.MINUTE, 0)\n\t        endCal.set(Calendar.SECOND, 0)\n\t        endCal.set(Calendar.MILLISECOND, 0)\n\t        end \u003d endCal.getTime()\n\t\n\t        event \u003d HashMap()\n\t        event[\"itemId\"] \u003d itemId\n\t        event[\"startDate\"] \u003d start\n\t        event[\"endDate\"] \u003d end\n\t        events.add(event)\n\t\n\treturn events",
                  "type": "script"
                }
              ],
              "type": "expr"
            }
          },
          "props.items": {
            "binding": {
              "config": {
                "polling": {
                  "enabled": true,
                  "rate": "3"
                },
                "queryPath": "SchedulerNames",
                "returnFormat": "json"
              },
              "type": "query"
            }
          },
          "props.scheduledEvents": {
            "binding": {
              "config": {
                "polling": {
                  "enabled": true,
                  "rate": "3"
                },
                "queryPath": "join1-EmpReq",
                "returnFormat": "json"
              },
              "type": "query"
            },
            "persistent": false
          },
          "props.selectedEventStyle": {
            "binding": {
              "config": {
                "expression": "{session.custom.swap}"
              },
              "transforms": [
                {
                  "code": "\tswap \u003d value  # value is {view.params.swap}\n\tif swap \u003d\u003d 1:\n\t\treturn {\"backgroundColor\": \"#4CAF50\", \"color\": \"#FFFFFF\"}\n\telse:\n\t\treturn {}",
                  "type": "script"
                }
              ],
              "type": "expr"
            }
          }
        },
        "props": {
          "dateRange": {},
          "progressBar": {
            "enabled": false
          },
          "selectedEvent": {
            "eventId": 401,
            "itemId": 3
          },
          "style": {
            "borderBottomLeftRadius": 10,
            "borderBottomRightRadius": 10,
            "borderStyle": "solid",
            "borderTopLeftRadius": 10,
            "borderTopRightRadius": 10,
            "outlineStyle": "solid",
            "paddingBottom": 2,
            "paddingLeft": 2,
            "paddingRight": 2,
            "paddingTop": 2
          }
        },
        "type": "ia.display.equipmentschedule"
      },
      {
        "events": {
          "dom": {
            "onClick": [
              {
                "config": {
                  "draggable": false,
                  "id": "SXfGZFK0",
                  "modal": false,
                  "overlayDismiss": false,
                  "position": {
                    "relativeLocation": "bottom"
                  },
                  "positionType": "relative",
                  "resizable": true,
                  "showCloseIcon": false,
                  "type": "open",
                  "viewPath": "SwapPopup",
                  "viewportBound": false
                },
                "scope": "C",
                "type": "popup"
              },
              {
                "config": {
                  "script": "\tself.session.custom.swap\u003d1"
                },
                "scope": "G",
                "type": "script"
              }
            ]
          }
        },
        "meta": {
          "name": "Button_2"
        },
        "position": {
          "height": 0.045,
          "width": 0.0859,
          "x": 0.8957,
          "y": 0.4997
        },
        "propConfig": {
          "props.enabled": {
            "binding": {
              "config": {
                "expression": "if({session.props.auth.user.roles[0]} \u003d \u0027Administrator\u0027,true,false)"
              },
              "type": "expr"
            }
          }
        },
        "props": {
          "image": {
            "icon": {
              "color": "#8AFFFF"
            },
            "style": {
              "fill": "#FF0000"
            }
          },
          "text": "Swap"
        },
        "type": "ia.input.button"
      },
      {
        "meta": {
          "name": "Label_4"
        },
        "position": {
          "height": 0.0564,
          "width": 0.1229,
          "x": 0.7671,
          "y": 0.4959
        },
        "props": {
          "style": {
            "fontSize": 20
          },
          "text": "Swap schedules",
          "textStyle": {
            "color": "#00AC00",
            "fontFamily": "serif",
            "fontStyle": "italic",
            "fontWeight": "bold"
          }
        },
        "type": "ia.display.label"
      }
    ],
    "meta": {
      "name": "root"
    },
    "props": {
      "mode": "percent"
    },
    "type": "ia.container.coord"
  }
}